asterisk/__init__.py
asterisk/ami/__init__.py
asterisk/ami/action.py
asterisk/ami/client.py
asterisk/ami/event.py
asterisk/ami/response.py
asterisk/ami/utils.py
asterisk_ami-0.1.7.dist-info/LICENSE
asterisk_ami-0.1.7.dist-info/METADATA
asterisk_ami-0.1.7.dist-info/WHEEL
asterisk_ami-0.1.7.dist-info/top_level.txt
asterisk_ami-0.1.7.dist-info/RECORD
