Metadata-Version: 2.1
Name: asterisk-ami
Version: 0.1.7
Summary: Python AMI Client
Author-email: Ettore Leandro Tognoli <ettore.leandro.tognoli@gmail.com>
Project-URL: Homepage, https://github.com/ettoreleandrotognoli/python-ami
Project-URL: Bug Tracker, https://github.com/ettoreleandrotognoli/python-ami/issues
Keywords: asterisk,ami
Classifier: Operating System :: OS Independent
Classifier: Programming Language :: Python
Classifier: Programming Language :: Python :: 2
Classifier: Programming Language :: Python :: 3
Classifier: Development Status :: 3 - Alpha
Classifier: License :: OSI Approved :: BSD License
License-File: LICENSE
Provides-Extra: tests
Requires-Dist: rx; extra == "tests"
Requires-Dist: coverage; extra == "tests"
